patch_based_inpainting/__init__.py
patch_based_inpainting/inpaint.py
patch_based_inpainting-0.0.3.dist-info/LICENSE
patch_based_inpainting-0.0.3.dist-info/METADATA
patch_based_inpainting-0.0.3.dist-info/WHEEL
patch_based_inpainting-0.0.3.dist-info/top_level.txt
patch_based_inpainting-0.0.3.dist-info/RECORD
